Metadata-Version: 2.1
Name: dni-pypi-test-1
Version: 0.1.0
Summary: Deal with Spanish DNIs in a Pythonic way.
Home-page: https://github.com/pmartincalvo/dni
Author: Pablo Martin Calvo
Author-email: pablomartincalvo+dni@gmail.com
License: LICENSE
Platform: UNKNOWN
